Metadata-Version: 2.4
Name: spec-kitty-cli-jl
Version: 0.12.2
Summary: Fork of Spec Kitty for testing
Project-URL: Repository, https://github.com/jlacube/spec-kitty
Project-URL: Issues, https://github.com/jlacube/spec-kitty/issues
Project-URL: Documentation, https://spec-kitty.github.io/spec-kit
Project-URL: Changelog, https://github.com/jlacube/spec-kitty/blob/main/CHANGELOG.md
Author: Jerome Lacube
Maintainer: Jerome Lacube
License: MIT License
License-File: LICENSE
Keywords: agentic-development,ai-agents,ai-coding,claude-code,cli,code-generation,feature-specs,git-worktree,kanban,llm-tools,planning,requirements,sdd,spec-driven-development,specification,workflow-automation
Classifier: Development Status :: 4 - Beta
Classifier: Environment :: Console
Classifier: Intended Audience :: Developers
Classifier: License :: OSI Approved :: MIT License
Classifier: Operating System :: OS Independent
Classifier: Programming Language :: Python :: 3
Classifier: Programming Language :: Python :: 3.11
Classifier: Programming Language :: Python :: 3.12
Classifier: Programming Language :: Python :: 3.13
Classifier: Topic :: Software Development
Classifier: Topic :: Software Development :: Code Generators
Classifier: Topic :: Software Development :: Documentation
Classifier: Topic :: Software Development :: Quality Assurance
Classifier: Topic :: Software Development :: Version Control
Classifier: Topic :: Software Development :: Version Control :: Git
Classifier: Topic :: Utilities
Classifier: Typing :: Typed
Requires-Python: >=3.11
Requires-Dist: httpx[socks]
Requires-Dist: packaging>=23.0
Requires-Dist: platformdirs
Requires-Dist: pydantic>=2.0
Requires-Dist: pyyaml>=6.0
Requires-Dist: readchar
Requires-Dist: rich
Requires-Dist: ruamel-yaml>=0.18.0
Requires-Dist: truststore>=0.10.4
Requires-Dist: typer
Provides-Extra: test
Requires-Dist: pytest>=7.4; extra == 'test'
